example_scripts/plot_LOFAR_beams.py
example_scripts/__pycache__/plot_LOFAR_beams.cpython-311.pyc
files/LOFAR_EoR_template.MS/table.dat
files/LOFAR_EoR_template.MS/table.f0
files/LOFAR_EoR_template.MS/table.f1
files/LOFAR_EoR_template.MS/table.f1i
files/LOFAR_EoR_template.MS/table.f2
files/LOFAR_EoR_template.MS/table.f2_TSM0
files/LOFAR_EoR_template.MS/table.f3
files/LOFAR_EoR_template.MS/table.f3_TSM0
files/LOFAR_EoR_template.MS/table.f4
files/LOFAR_EoR_template.MS/table.f4_TSM0
files/LOFAR_EoR_template.MS/table.f5
files/LOFAR_EoR_template.MS/table.f5_TSM0
files/LOFAR_EoR_template.MS/table.info
files/LOFAR_EoR_template.MS/table.lock
files/LOFAR_EoR_template.MS/ANTENNA/table.dat
files/LOFAR_EoR_template.MS/ANTENNA/table.f0
files/LOFAR_EoR_template.MS/ANTENNA/table.info
files/LOFAR_EoR_template.MS/ANTENNA/table.lock
files/LOFAR_EoR_template.MS/DATA_DESCRIPTION/table.dat
files/LOFAR_EoR_template.MS/DATA_DESCRIPTION/table.f0
files/LOFAR_EoR_template.MS/DATA_DESCRIPTION/table.info
files/LOFAR_EoR_template.MS/DATA_DESCRIPTION/table.lock
files/LOFAR_EoR_template.MS/FEED/table.dat
files/LOFAR_EoR_template.MS/FEED/table.f0
files/LOFAR_EoR_template.MS/FEED/table.f0i
files/LOFAR_EoR_template.MS/FEED/table.info
files/LOFAR_EoR_template.MS/FEED/table.lock
files/LOFAR_EoR_template.MS/FIELD/table.dat
files/LOFAR_EoR_template.MS/FIELD/table.f0
files/LOFAR_EoR_template.MS/FIELD/table.f0i
files/LOFAR_EoR_template.MS/FIELD/table.info
files/LOFAR_EoR_template.MS/FIELD/table.lock
files/LOFAR_EoR_template.MS/FLAG_CMD/table.dat
files/LOFAR_EoR_template.MS/FLAG_CMD/table.f0
files/LOFAR_EoR_template.MS/FLAG_CMD/table.info
files/LOFAR_EoR_template.MS/FLAG_CMD/table.lock
files/LOFAR_EoR_template.MS/HISTORY/table.dat
files/LOFAR_EoR_template.MS/HISTORY/table.f0
files/LOFAR_EoR_template.MS/HISTORY/table.info
files/LOFAR_EoR_template.MS/HISTORY/table.lock
files/LOFAR_EoR_template.MS/LOFAR_ANTENNA_FIELD/table.dat
files/LOFAR_EoR_template.MS/LOFAR_ANTENNA_FIELD/table.f0
shimmerr-1.0.1.dist-info/licenses/LICENSE
shimmerr-1.0.1.dist-info/METADATA
shimmerr-1.0.1.dist-info/WHEEL
shimmerr-1.0.1.dist-info/top_level.txt
shimmerr-1.0.1.dist-info/RECORD
