Metadata-Version: 2.4
Name: shimmerr
Version: 1.0.1
Summary: SHIMMERR (Station Heterogeneity Impact on Multi-dimensional beam-Modelling Errors simulatoR and calibratoR) is a python package created to simulate the effect of beam errors on hierarchical stations in radio-interferometers.
Author-email: Stefanie Brackenhoff <brackenhoff@astro.rug.nl>
License-Expression: MIT
Project-URL: Homepage, https://github.com/Stefanie-B/shimmerr
Project-URL: Issues, https://github.com/Stefanie-B/shimmerr/issues
Classifier: Programming Language :: Python :: 3
Classifier: Operating System :: OS Independent
Requires-Python: >=3.11
License-File: LICENSE
Requires-Dist: scipy
Requires-Dist: astropy
Requires-Dist: lofarantpos
Requires-Dist: matplotlib
Requires-Dist: numba
Requires-Dist: numpy
Requires-Dist: pandas
Requires-Dist: tqdm
Dynamic: license-file
